ricgraph/__init__.py
ricgraph/ricgraph.py
ricgraph/ricgraph_cache.py
ricgraph/ricgraph_constants.py
ricgraph/ricgraph_cypher.py
ricgraph/ricgraph_file.py
ricgraph/ricgraph_graphdb.py
ricgraph/ricgraph_harvest.py
ricgraph/ricgraph_researchinfo.py
ricgraph/ricgraph_restapi.py
ricgraph/ricgraph_utils.py
ricgraph-3.1.dist-info/licenses/LICENSE
ricgraph-3.1.dist-info/METADATA
ricgraph-3.1.dist-info/WHEEL
ricgraph-3.1.dist-info/top_level.txt
ricgraph-3.1.dist-info/RECORD
