Metadata-Version: 2.4
Name: ricgraph
Version: 3.1
Summary: Ricgraph - Research in context graph
Author: Rik D.T. Janssen
License-Expression: MIT
Project-URL: Website, https://www.ricgraph.eu
Project-URL: Documentation, https://docs.ricgraph.eu
Project-URL: GitHub, https://github.com/UtrechtUniversity/ricgraph
Project-URL: Issues, https://github.com/UtrechtUniversity/ricgraph/issues
Project-URL: Download, https://github.com/UtrechtUniversity/ricgraph/releases
Project-URL: Release Notes, https://github.com/UtrechtUniversity/ricgraph/releases
Keywords: Research in context graph,Ricgraph,Ricgraph Explorer,Ricgraph REST API,Data enrichment,Data harvesting,Data linking,Enrichment,Graph,Graph database,Harvest,Harvest data,Harvester,Knowledge graph,Linked data,Metadata,Utrecht University,Visualization
Classifier: Development Status :: 5 - Production/Stable
Classifier: Operating System :: OS Independent
Classifier: Programming Language :: Python :: 3
Requires-Python: >=3.9
License-File: LICENSE
Requires-Dist: neo4j>=5.8
Requires-Dist: numpy
Requires-Dist: pandas
Requires-Dist: requests
Requires-Dist: unidecode
Dynamic: license-file
